{
  "minecraft:recipes/decorations/crafting_table": {
    "criteria": {
      "unlock_right_away": "2025-01-07 00:54:12 +0000"
    },
    "done": true
  },
  "minecraft:recipes/building_blocks/spruce_wood": {
    "criteria": {
      "has_log": "2025-01-07 00:56:59 +0000"
    },
    "done": true
  },
  "betterdeserttemples:root": {
    "criteria": {
      "always": "2025-01-07 00:54:12 +0000"
    },
    "done": true
  },
  "cataclysm:root": {
    "criteria": {
      "custom_test_name": "2025-01-07 00:54:12 +0000"
    },
    "done": true
  },
  "minecraft:recipes/building_blocks/spruce_planks": {
    "criteria": {
      "has_logs": "2025-01-07 00:56:59 +0000"
    },
    "done": true
  },
  "dungeons_arise:wda_root": {
    "criteria": {
      "WDA": "2025-01-07 00:54:12 +0000"
    },
    "done": true
  },
  "minecraft:recipes/misc/charcoal": {
    "criteria": {
      "has_log": "2025-01-07 00:56:59 +0000"
    },
    "done": true
  },
  "mcwdoors:recipes/spruce": {
    "criteria": {
      "has_wood": "2025-01-07 00:56:59 +0000"
    },
    "done": true
  },
  "minecraft:adventure/adventuring_time": {
    "criteria": {
      "minecraft:snowy_taiga": "2025-01-07 00:54:13 +0000"
    },
    "done": false
  },
  "DataVersion": 3465
}